kanata/__init__.py
kanata/constants.py
kanata/ilifetime_scope.py
kanata/injectable_discovery.py
kanata/lifetime_scope.py
kanata/catalogs/__init__.py
kanata/catalogs/iinjectable_catalog.py
kanata/catalogs/injectable_catalog.py
kanata/catalogs/injectable_catalog_builder.py
kanata/decorators/__init__.py
kanata/decorators/injectable.py
kanata/decorators/scope.py
kanata/exceptions/__init__.py
kanata/exceptions/argument_exception.py
kanata/exceptions/dependency_resolution_exception.py
kanata/exceptions/injectable_registration_exception.py
kanata/graphs/__init__.py
kanata/graphs/bidirected_graph.py
kanata/graphs/edge.py
kanata/graphs/graph.py
kanata/graphs/tnode.py
kanata/graphs/exceptions/__init__.py
kanata/graphs/exceptions/cyclic_graph_exception.py
kanata/graphs/exceptions/disconnected_sub_graph_exception.py
kanata/graphs/exceptions/duplicate_edge_exception.py
kanata/graphs/exceptions/duplicate_node_exception.py
kanata/graphs/sorting/__init__.py
kanata/graphs/sorting/topological_sorter.py
kanata/models/__init__.py
kanata/models/closed_generic_type_id.py
kanata/models/closed_generic_type_info.py
kanata/models/iinstance_collection.py
kanata/models/injectable_instance_registration.py
kanata/models/injectable_registration.py
kanata/models/injectable_scope_type.py
kanata/models/injectable_type_registration.py
kanata/models/instance_collection.py
kanata/resolvers/__init__.py
kanata/resolvers/default_resolver.py
kanata/resolvers/default_resolver_options.py
kanata/resolvers/iresolver.py
kanata/resolvers/resolver_base.py
kanata/resolvers/resolver_context.py
kanata/utils/__init__.py
kanata/utils/dict_utils.py
kanata/utils/type_utils.py
kanata-4.0.0.0.dist-info/LICENSE
kanata-4.0.0.0.dist-info/METADATA
kanata-4.0.0.0.dist-info/WHEEL
kanata-4.0.0.0.dist-info/top_level.txt
kanata-4.0.0.0.dist-info/RECORD
