Metadata-Version: 2.1
Name: kanata
Version: 4.0.0.0
Summary: A simple dependency injection framework for Python 3 applications.
Home-page: https://github.com/rexor12/kanata
Author: rexor12
Author-email: rrexor@gmail.com
Project-URL: Bug Tracker, https://github.com/rexor12/kanata/issues
Classifier: Programming Language :: Python :: 3
Classifier: License :: OSI Approved :: MIT License
Classifier: Operating System :: OS Independent
Requires-Python: >=3.11
License-File: LICENSE
Requires-Dist: structlog <25,>=22.3
